todoist_to_todotxt/__init__.py
todoist_to_todotxt/main.py
todoist_to_todotxt-0.1.1.dist-info/licenses/LICENSE.txt
todoist_to_todotxt-0.1.1.dist-info/METADATA
todoist_to_todotxt-0.1.1.dist-info/WHEEL
todoist_to_todotxt-0.1.1.dist-info/entry_points.txt
todoist_to_todotxt-0.1.1.dist-info/top_level.txt
todoist_to_todotxt-0.1.1.dist-info/RECORD
