Metadata-Version: 2.4
Name: todoist-to-todotxt
Version: 0.1.1
Summary: Save tasks from Todoist to todo.txt format
Author: Anton Larionov
License: MIT License
Project-URL: Homepage, https://github.com/anlar/todoist-to-todotxt
Project-URL: Repository, https://github.com/anlar/todoist-to-todotxt
Project-URL: Bug Tracker, https://github.com/anlar/todoist-to-todotxt/issues
Keywords: todoist,todo.txt
Classifier: Programming Language :: Python :: 3
Classifier: License :: OSI Approved :: MIT License
Classifier: Operating System :: OS Independent
Requires-Python: >=3.7
License-File: LICENSE.txt
Requires-Dist: requests
Dynamic: license-file
